{
  "locale": {
    "fr-CA": {
      "label": "Binoculaire",
      "fields": [
        {
          "name": "Phorias",
          "label": "Phories",
          "fields": [
            {
              "name": "Distant vision",
              "label": "VL"
            },
            {
              "name": "Near vision",
              "label": "VP"
            }
          ]
        },
        {
          "name": "Vergence BI",
          "fields": [
            {
              "name": "Distant",
              "label": "VL",
              "fields": [
                {
                  "name": "Blur",
                  "label": "Embrouill."
                },
                {
                  "name": "Break",
                  "label": "Bris"
                },
                {
                  "name": "Recov.",
                  "label": "Recouv."
                }
              ]
            },
            {
              "name": "Near",
              "label": "VP",
              "fields": [
                {
                  "name": "Blur",
                  "label": "Embrouill."
                },
                {
                  "name": "Break",
                  "label": "Bris"
                },
                {
                  "name": "Recov.",
                  "label": "Recouv."
                }
              ]
            }
          ],
          "size": "M"
        },
        {
          "name": "Vergence BO",
          "label": "Vergence BE",
          "fields": [
            {
              "name": "Distant",
              "label": "VL",
              "fields": [
                {
                  "name": "Blur",
                  "label": "Embrouil."
                },
                {
                  "name": "Break",
                  "label": "Bris"
                },
                {
                  "name": "Recov.",
                  "label": "Recouv."
                }
              ]
            },
            {
              "name": "Near",
              "label": "VP",
              "fields": [
                {
                  "name": "Blur",
                  "label": "Embrouil."
                },
                {
                  "name": "Break",
                  "label": "Bris"
                },
                {
                  "name": "Recov.",
                  "label": "Recouv."
                }
              ]
            }
          ],
          "size": "M"
        },
        {
          "name": "Vergence BU",
          "label": "Vergence BH",
          "fields": [
            {
              "name": "Distant",
              "label": "VL",
              "fields": [
                {
                  "name": "Blur",
                  "label": "Embrouil."
                },
                {
                  "name": "Break",
                  "label": "Bris"
                },
                {
                  "name": "Recov.",
                  "label": "Recouv."
                }
              ]
            },
            {
              "name": "Near",
              "label": "VP",
              "fields": [
                {
                  "name": "Blur",
                  "label": "Embrouil."
                },
                {
                  "name": "Break",
                  "label": "Bris"
                },
                {
                  "name": "Recov.",
                  "label": "Recouv."
                }
              ]
            }
          ],
          "size": "M"
        },
        {
          "name": "Vergence BD",
          "label": "Vergence BB",
          "fields": [
            {
              "name": "Distant",
              "label": "VL",
              "fields": [
                {
                  "name": "Blur",
                  "label": "Embrouil."
                },
                {
                  "name": "Break",
                  "label": "Bris"
                },
                {
                  "name": "Recov.",
                  "label": "Recouv."
                }
              ]
            },
            {
              "name": "Near",
              "label": "VP",
              "fields": [
                {
                  "name": "Blur",
                  "label": "Embrouil."
                },
                {
                  "name": "Break",
                  "label": "Bris"
                },
                {
                  "name": "Recov.",
                  "label": "Recouv."
                }
              ]
            }
          ],
          "size": "M"
        },
        {
          "name": "Pursuits",
          "label": "Poursuites",
          "fields": [
            {
              "name": "OD",
              "normalValue": "Smooth and precise",
              "options": ["Smooth and precise"]
            },
            {
              "name": "OS",
              "normalValue": "Smooth and precise",
              "options": ["Smooth and precise"]
            }
          ]
        },
        {
          "name": "Saccades",
          "fields": [
            {
              "name": "OD",
              "normalValue": "Smooth and precise",
              "options": ["Smooth and precise"]
            },
            {
              "name": "OS",
              "normalValue": "Smooth and precise",
              "options": ["Smooth and precise"]
            }
          ]
        }
      ]
    }
  },
  "name": "Binocular",
  "scrollable": true,
  "starable": true,
  "type": "groupedForm",
  "section": "Vision testing.5",
  "relatedExams": ["Cover test"],
  "fields": [
    {
      "name": "Phorias",
      "columns": [["Distant vision", "Near vision"]],
      "fields": [
        {
          "name": "Distant vision",
          "fields": [
            {
              "name": "H",
              "minValue": 0,
              "suffix": " \u0394",
              "maxValue": 50,
              "options": ["Ortho"]
            },
            {
              "name": "V",
              "minValue": 0,
              "suffix": " \u0394",
              "maxValue": 20,
              "options": ["Ortho"]
            }
          ]
        },
        {
          "name": "Near vision",
          "fields": [
            {
              "name": "H",
              "minValue": 0,
              "suffix": " \u0394",
              "maxValue": 50,
              "options": ["Ortho"]
            },
            {
              "name": "V",
              "minValue": 0,
              "suffix": " \u0394",
              "maxValue": 20,
              "options": ["Ortho"]
            }
          ]
        }
      ],
      "size": "S"
    },
    {
      "name": "Vergence BI",
      "columns": [["Distant", "Near"]],
      "fields": [
        {
          "name": "Distant",
          "fields": [
            {
              "name": "Blur",
              "minValue": 0,
              "freestyle": true,
              "suffix": " \u0394",
              "options": ["X"],
              "maxValue": 50
            },
            {
              "name": "Break",
              "minValue": 0,
              "freestyle": true,
              "suffix": " \u0394",
              "maxValue": 50
            },
            {
              "name": "Recov.",
              "minValue": 0,
              "freestyle": true,
              "suffix": " \u0394",
              "maxValue": 50
            }
          ]
        },
        {
          "name": "Near",
          "fields": [
            {
              "name": "Blur",
              "minValue": 0,
              "freestyle": true,
              "suffix": " \u0394",
              "options": ["X"],
              "maxValue": 50
            },
            {
              "name": "Break",
              "minValue": 0,
              "freestyle": true,
              "suffix": " \u0394",
              "maxValue": 50
            },
            {
              "name": "Recov.",
              "minValue": 0,
              "freestyle": true,
              "suffix": " \u0394",
              "maxValue": 50
            }
          ]
        }
      ],
      "size": "S"
    },
    {
      "name": "Vergence BO",
      "columns": [["Distant", "Near"]],
      "fields": [
        {
          "name": "Distant",
          "fields": [
            {
              "name": "Blur",
              "minValue": 0,
              "freestyle": true,
              "suffix": " \u0394",
              "options": ["X"],
              "maxValue": 50
            },
            {
              "name": "Break",
              "minValue": 0,
              "freestyle": true,
              "suffix": " \u0394",
              "maxValue": 50
            },
            {
              "name": "Recov.",
              "minValue": 0,
              "freestyle": true,
              "suffix": " \u0394",
              "maxValue": 50
            }
          ]
        },
        {
          "name": "Near",
          "fields": [
            {
              "name": "Blur",
              "minValue": 0,
              "freestyle": true,
              "suffix": " \u0394",
              "options": ["X"],
              "maxValue": 50
            },
            {
              "name": "Break",
              "minValue": 0,
              "freestyle": true,
              "suffix": " \u0394",
              "maxValue": 50
            },
            {
              "name": "Recov.",
              "minValue": 0,
              "freestyle": true,
              "suffix": " \u0394",
              "maxValue": 50
            }
          ]
        }
      ],
      "size": "S"
    },
    {
      "optional": true,
      "name": "Vergence BU",
      "columns": [["Distant", "Near"]],
      "fields": [
        {
          "name": "Distant",
          "fields": [
            {
              "name": "Blur",
              "minValue": 0,
              "freestyle": true,
              "suffix": " \u0394",
              "options": ["X"],
              "maxValue": 50
            },
            {
              "name": "Break",
              "minValue": 0,
              "freestyle": true,
              "suffix": " \u0394",
              "maxValue": 50
            },
            {
              "name": "Recov.",
              "minValue": 0,
              "freestyle": true,
              "suffix": " \u0394",
              "maxValue": 50
            }
          ]
        },
        {
          "name": "Near",
          "fields": [
            {
              "name": "Blur",
              "minValue": 0,
              "freestyle": true,
              "suffix": " \u0394",
              "options": ["X"],
              "maxValue": 50
            },
            {
              "name": "Break",
              "minValue": 0,
              "freestyle": true,
              "suffix": " \u0394",
              "maxValue": 50
            },
            {
              "name": "Recov.",
              "minValue": 0,
              "freestyle": true,
              "suffix": " \u0394",
              "maxValue": 50
            }
          ]
        }
      ],
      "size": "S"
    },
    {
      "optional": true,
      "name": "Vergence BD",
      "columns": [["Distant", "Near"]],
      "fields": [
        {
          "name": "Distant",
          "fields": [
            {
              "name": "Blur",
              "minValue": 0,
              "freestyle": true,
              "suffix": " \u0394",
              "options": ["X"],
              "maxValue": 50
            },
            {
              "name": "Break",
              "minValue": 0,
              "freestyle": true,
              "suffix": " \u0394",
              "maxValue": 50
            },
            {
              "name": "Recov.",
              "minValue": 0,
              "freestyle": true,
              "suffix": " \u0394",
              "maxValue": 50
            }
          ]
        },
        {
          "name": "Near",
          "fields": [
            {
              "name": "Blur",
              "minValue": 0,
              "freestyle": true,
              "suffix": " \u0394",
              "options": ["X"],
              "maxValue": 50
            },
            {
              "name": "Break",
              "minValue": 0,
              "freestyle": true,
              "suffix": " \u0394",
              "maxValue": 50
            },
            {
              "name": "Recov.",
              "minValue": 0,
              "freestyle": true,
              "suffix": " \u0394",
              "maxValue": 50
            }
          ]
        }
      ],
      "size": "S"
    },
    {
      "optional": false,
      "name": "Accomodation",
      "columns": [["OD", "OS"]],
      "fields": [
        {
          "name": "OD",
          "fields": [
            {
              "minValue": 1,
              "name": "Amp.",
              "freestyle": true,
              "suffix": " D",
              "maxValue": 20
            }
          ]
        },
        {
          "name": "OS",
          "fields": [
            {
              "minValue": 1,
              "name": "Amp.",
              "freestyle": true,
              "suffix": " D",
              "maxValue": 20
            }
          ]
        },
        {
          "minValue": 1,
          "name": "AC/A ratio",
          "freestyle": true,
          "suffix": ":1",
          "maxValue": 20
        },
        {
          "decimals": 2,
          "stepSize": 0.25,
          "name": "NRA",
          "prefix": "+",
          "minValue": -10,
          "freestyle": true,
          "maxValue": 10
        },
        {
          "decimals": 2,
          "stepSize": 0.25,
          "name": "PRA",
          "prefix": "+",
          "minValue": -10,
          "freestyle": true,
          "maxValue": 10
        }
      ]
    },
    {
      "optional": true,
      "name": "Pursuits",
      "size": "S",
      "fields": [
        {
          "normalValue": "Smooth and precise",
          "name": "OD",
          "freestyle": true,
          "options": ["Smooth and precise"]
        },
        {
          "normalValue": "Smooth and precise",
          "name": "OS",
          "freestyle": true,
          "options": ["Smooth and precise"]
        }
      ]
    },
    {
      "optional": true,
      "name": "Saccades",
      "size": "S",
      "fields": [
        {
          "normalValue": "Smooth and precise",
          "name": "OD",
          "freestyle": true,
          "options": ["Smooth and precise"]
        },
        {
          "normalValue": "Smooth and precise",
          "name": "OS",
          "freestyle": true,
          "options": ["Smooth and precise"]
        }
      ]
    },
    {
      "optional": true,
      "name": "Notes",
      "size": "L",
      "fields": [
        {
          "maxLength": 500,
          "name": "Notes",
          "label": "",
          "freestyle": true
        }
      ]
    }
  ]
}
